cli/__init__.py
cli/main.py
cli/models.py
cli/patent_cli.py
cli/rich_agents_main.py
cli/rich_agents_simple.py
cli/trading_cli.py
cli/utils.py
patentagents/__init__.py
rich_agents-0.2.0.dist-info/licenses/LICENSE
shared/__init__.py
shared/cache/__init__.py
shared/config/__init__.py
shared/config/rich_agents_config_manager.py
shared/llm_adapters/__init__.py
shared/llm_adapters/unified_llm_adapter.py
shared/utils/__init__.py
tradingagents/default_config.py
rich_agents-0.2.0.dist-info/METADATA
rich_agents-0.2.0.dist-info/WHEEL
rich_agents-0.2.0.dist-info/entry_points.txt
rich_agents-0.2.0.dist-info/top_level.txt
rich_agents-0.2.0.dist-info/RECORD
