Metadata-Version: 2.4
Name: rich-agents
Version: 0.2.0
Summary: Rich-Agents: 统一多智能体AI工具集 - 支持金融交易分析和专利智能体
Home-page: https://github.com/chenxingqiang
Author: TradingAgents Team
Author-email: Turingai Team <chenxingqiang@turingai.cc>
Maintainer-email: Turingai Team <chenxingqiang@turingai.cc>
License-Expression: MIT
Project-URL: Homepage, https://github.com/chenxingqiang/TradingAgents
Project-URL: Repository, https://github.com/chenxingqiang/TradingAgents
Project-URL: Documentation, https://github.com/chenxingqiang/TradingAgents/docs
Project-URL: Issues, https://github.com/chenxingqiang/TradingAgents/issues
Project-URL: Changelog, https://github.com/chenxingqiang/TradingAgents/releases
Keywords: artificial-intelligence,multi-agent,trading,patent,llm,financial-analysis,patent-analysis,ai-toolkit
Classifier: Development Status :: 4 - Beta
Classifier: Intended Audience :: Developers
Classifier: Intended Audience :: Financial and Insurance Industry
Classifier: Intended Audience :: Science/Research
Classifier: Operating System :: OS Independent
Classifier: Programming Language :: Python :: 3
Classifier: Programming Language :: Python :: 3.10
Classifier: Programming Language :: Python :: 3.11
Classifier: Programming Language :: Python :: 3.12
Classifier: Topic :: Scientific/Engineering :: Artificial Intelligence
Classifier: Topic :: Office/Business :: Financial
Classifier: Topic :: Scientific/Engineering :: Information Analysis
Requires-Python: >=3.10
License-File: LICENSE
Requires-Dist: akshare>=1.16.98
Requires-Dist: backtrader>=1.9.78.123
Requires-Dist: chainlit>=2.5.5
Requires-Dist: chromadb>=1.0.12
Requires-Dist: eodhd>=1.0.32
Requires-Dist: feedparser>=6.0.11
Requires-Dist: finnhub-python>=2.4.23
Requires-Dist: langchain-anthropic>=0.3.15
Requires-Dist: langchain-experimental>=0.3.4
Requires-Dist: langchain-google-genai>=2.1.5
Requires-Dist: langchain-openai>=0.3.23
Requires-Dist: httpx[socks]>=0.25.0
Requires-Dist: langgraph>=0.4.8
Requires-Dist: pandas>=2.3.0
Requires-Dist: parsel>=1.10.0
Requires-Dist: praw>=7.8.1
Requires-Dist: pytz>=2025.2
Requires-Dist: questionary>=2.1.0
Requires-Dist: redis>=6.2.0
Requires-Dist: requests>=2.32.4
Requires-Dist: rich>=14.0.0
Requires-Dist: setuptools>=80.9.0
Requires-Dist: stockstats>=0.6.5
Requires-Dist: tqdm>=4.67.1
Requires-Dist: tushare>=1.4.21
Requires-Dist: typing-extensions>=4.14.0
Requires-Dist: yfinance>=0.2.63
Provides-Extra: trading
Requires-Dist: yfinance>=0.2.63; extra == "trading"
Requires-Dist: finnhub-python>=2.4.23; extra == "trading"
Requires-Dist: akshare>=1.16.98; extra == "trading"
Requires-Dist: stockstats>=0.6.5; extra == "trading"
Requires-Dist: pytdx>=1.72; extra == "trading"
Provides-Extra: patent
Requires-Dist: google-search-results>=2.4.2; extra == "patent"
Requires-Dist: beautifulsoup4>=4.9.0; extra == "patent"
Provides-Extra: chinese
Requires-Dist: pytdx>=1.72; extra == "chinese"
Requires-Dist: dashscope>=1.0.0; extra == "chinese"
Provides-Extra: database
Requires-Dist: pymongo>=4.0.0; extra == "database"
Requires-Dist: redis>=6.2.0; extra == "database"
Provides-Extra: visualization
Requires-Dist: streamlit>=1.28.0; extra == "visualization"
Requires-Dist: plotly>=5.0.0; extra == "visualization"
Provides-Extra: cli
Requires-Dist: typer>=0.12.0; extra == "cli"
Requires-Dist: rich>=14.0.0; extra == "cli"
Provides-Extra: development
Requires-Dist: pytest>=7.0.0; extra == "development"
Requires-Dist: pytest-cov>=4.0.0; extra == "development"
Requires-Dist: black>=23.0.0; extra == "development"
Requires-Dist: flake8>=6.0.0; extra == "development"
Requires-Dist: mypy>=1.0.0; extra == "development"
Requires-Dist: pre-commit>=3.0.0; extra == "development"
Provides-Extra: all
Requires-Dist: yfinance>=0.2.63; extra == "all"
Requires-Dist: finnhub-python>=2.4.23; extra == "all"
Requires-Dist: akshare>=1.16.98; extra == "all"
Requires-Dist: stockstats>=0.6.5; extra == "all"
Requires-Dist: pytdx>=1.72; extra == "all"
Requires-Dist: google-search-results>=2.4.2; extra == "all"
Requires-Dist: beautifulsoup4>=4.9.0; extra == "all"
Requires-Dist: dashscope>=1.0.0; extra == "all"
Requires-Dist: pymongo>=4.0.0; extra == "all"
Requires-Dist: redis>=6.2.0; extra == "all"
Requires-Dist: streamlit>=1.28.0; extra == "all"
Requires-Dist: plotly>=5.0.0; extra == "all"
Requires-Dist: typer>=0.12.0; extra == "all"
Dynamic: author
Dynamic: home-page
Dynamic: license-file
Dynamic: requires-python
